uht_DMSlibrarian/UMIC_seq.py
uht_DMSlibrarian/UMIC_seq_helper.py
uht_DMSlibrarian/__init__.py
uht_DMSlibrarian/cli.py
uht_DMSlibrarian/fitness_analysis.py
uht_DMSlibrarian/gui.py
uht_DMSlibrarian/ngs_count.py
uht_DMSlibrarian/reference_manager.py
uht_DMSlibrarian/sensitive_variant_pipeline.py
uht_DMSlibrarian/simple_consensus_pipeline.py
uht_DMSlibrarian/vcf2csv_detailed.py
uht_dmslibrarian-0.2.7.dist-info/licenses/LICENSE
uht_dmslibrarian-0.2.7.dist-info/METADATA
uht_dmslibrarian-0.2.7.dist-info/WHEEL
uht_dmslibrarian-0.2.7.dist-info/entry_points.txt
uht_dmslibrarian-0.2.7.dist-info/top_level.txt
uht_dmslibrarian-0.2.7.dist-info/RECORD
