Metadata-Version: 2.4
Name: uht-dmslibrarian
Version: 0.2.7
Summary: Extension of the UMIC-seq Pipeline - Complete pipeline for dictionary building and NGS count inetgration, with fitness calculations, error modelling and mutation analysis
Home-page: https://github.com/Matt115A/uht-DMSlibrarian-package
Author: Matt Penner
Author-email: Matt Penner <mp957@cam.ac.uk>
License: MIT
Keywords: bioinformatics,pacbio,umi,sequencing,variant,calling
Classifier: Development Status :: 4 - Beta
Classifier: Intended Audience :: Science/Research
Classifier: Topic :: Scientific/Engineering :: Bio-Informatics
Classifier: Programming Language :: Python :: 3.10
Requires-Python: >=3.10,<3.11
License-File: LICENSE
Requires-Dist: biopython==1.86
Requires-Dist: scikit-bio==0.7.0
Requires-Dist: numpy==2.2.1
Requires-Dist: pandas==2.3.3
Requires-Dist: matplotlib==3.10.7
Requires-Dist: seaborn==0.13.2
Requires-Dist: scipy==1.15.3
Requires-Dist: scikit-allel==1.3.13
Requires-Dist: tqdm==4.67.1
Requires-Dist: psutil==7.1.3
Requires-Dist: gradio>=4.0.0
Provides-Extra: dev
Requires-Dist: pytest; extra == "dev"
Requires-Dist: black; extra == "dev"
Requires-Dist: flake8; extra == "dev"
Dynamic: author
Dynamic: home-page
Dynamic: license-file
Dynamic: requires-python
